LICENSE.txt
MANIFEST.in
README.rst
agpl-3.0.txt
setup.cfg
setup.py
structurediff/ArgsHandler.py
structurediff/DataComparison.py
structurediff/DataFile.py
structurediff/FormatOutput.py
structurediff/__init__.py
structurediff/cli.py
structurediff.egg-info/PKG-INFO
structurediff.egg-info/SOURCES.txt
structurediff.egg-info/dependency_links.txt
structurediff.egg-info/entry_points.txt
structurediff.egg-info/requires.txt
structurediff.egg-info/top_level.txt