Metadata-Version: 1.1
Name: structurediff
Version: 1.0
Summary: structurediff is a diff utility for structured data files
Home-page: https://gitlab.com/Rtzq0/structurediff
Author: Jason Ritzke (@Rtzq0)
Author-email: jasonritzke@4loopz.com
License: AGPLv3+
Keywords: DeepDiff YAML JSON diff
Platform: UNKNOWN
Classifier: Development Status :: 4 - Beta
Classifier: Intended Audience :: System Administrators
Classifier: Topic :: Utilities
Classifier: License :: OSI Approved :: GNU Affero General Public License v3 or later (AGPLv3+)
Classifier: Programming Language :: Python :: 2.7
